pyflow_cse_asu/EvaluationMetrics.py
pyflow_cse_asu/Layers.py
pyflow_cse_asu/Model.py
pyflow_cse_asu/Utilities.py
pyflow_cse_asu/Visualizer.py
pyflow_cse_asu/__activations__.py
pyflow_cse_asu/dataset.py
pyflow_cse_asu/libraries.py
pyflow_cse_asu/loss.py
pyflow_cse_asu_exp_1-1.0.0.dist-info/LICENSE.txt
pyflow_cse_asu_exp_1-1.0.0.dist-info/METADATA
pyflow_cse_asu_exp_1-1.0.0.dist-info/WHEEL
pyflow_cse_asu_exp_1-1.0.0.dist-info/top_level.txt
pyflow_cse_asu_exp_1-1.0.0.dist-info/RECORD
